photoshoot/__init__.py
photoshoot/comp.py
photoshoot/core.py
photoshoot/plugin.py
photoshoot/storage/__init__.py
photoshoot/storage/gcs.py
photoshoot/storage/local.py
photoshoot-0.2.1.dist-info/METADATA
photoshoot-0.2.1.dist-info/WHEEL
photoshoot-0.2.1.dist-info/entry_points.txt
photoshoot-0.2.1.dist-info/licenses/LICENSE
photoshoot-0.2.1.dist-info/RECORD
