Metadata-Version: 2.3
Name: photoshoot
Version: 0.2.1
Summary: A pytest plugin for snapshot testing polars dataframes.
Project-URL: Repository, https://github.com/ngriffiths13/photoshoot
License-File: LICENSE
Requires-Python: >=3.8
Requires-Dist: polars>=1.3.0
Requires-Dist: pytest>=8.0.0
Provides-Extra: gcs
Requires-Dist: gcsfs>=2024.6.1; extra == 'gcs'
